setup.py
audoai/common/__init__.py
audoai/common/base_audo_client.py
audoai/common/exceptions.py
audoai/common/utils.py
audoai_common.egg-info/PKG-INFO
audoai_common.egg-info/SOURCES.txt
audoai_common.egg-info/dependency_links.txt
audoai_common.egg-info/requires.txt
audoai_common.egg-info/top_level.txt